LICENSE.txt
MANIFEST.in
README.txt
readme.md
setup.cfg
setup.py
zio.py
zio.egg-info/PKG-INFO
zio.egg-info/SOURCES.txt
zio.egg-info/dependency_links.txt
zio.egg-info/entry_points.txt
zio.egg-info/top_level.txt