Metadata-Version: 1.1
Name: zio
Version: 2.0.0
Summary: Unified io lib for pwning development written in python.
Home-page: https://github.com/zTrix/zio
Author: Wenlei Zhu
Author-email: i@ztrix.me
License: LICENSE.txt
Keywords: zio pwning io expect-like
Platform: UNKNOWN
Classifier: Development Status :: 5 - Production/Stable
Classifier: Environment :: Console
Classifier: Intended Audience :: Developers
Classifier: Operating System :: POSIX
Classifier: Operating System :: MacOS :: MacOS X
Classifier: Programming Language :: Python
Classifier: Programming Language :: Python :: 2.6
Classifier: Programming Language :: Python :: 2.7
Classifier: Programming Language :: Python :: 3.5
Classifier: Programming Language :: Python :: 3.6
Classifier: Programming Language :: Python :: 3.7
Classifier: Programming Language :: Python :: 3.8
Classifier: Topic :: Software Development
Classifier: Topic :: System
Classifier: Topic :: Terminals
Classifier: Topic :: Utilities
